SimpleFastCrud/__init__.py
SimpleFastCrud/crud.py
simplefastcrud-0.1.4.dist-info/licenses/LICENSE.md
simplefastcrud-0.1.4.dist-info/METADATA
simplefastcrud-0.1.4.dist-info/WHEEL
simplefastcrud-0.1.4.dist-info/top_level.txt
simplefastcrud-0.1.4.dist-info/RECORD
