Metadata-Version: 2.4
Name: SimpleFastCrud
Version: 0.1.4
Summary: SimpleFastCrud is a tool that simplifies the creation of dynamic CRUD endpoints in FastAPI using SQLAlchemy and Pydantic.
Author-email: Miguel Bustamante <miguelbustamantef@gmail.com>
License: MIT License
Project-URL: Homepage, https://github.com/miguelebf/SimpleFastCrud
Project-URL: Bug Tracker, https://github.com/miguelebf/SimpleFastCrud/issues
Classifier: License :: OSI Approved :: MIT License
Classifier: Programming Language :: Python :: 3
Classifier: Programming Language :: Python :: 3.7
Classifier: Programming Language :: Python :: 3.8
Classifier: Programming Language :: Python :: 3.9
Classifier: Programming Language :: Python :: 3.10
Classifier: Programming Language :: Python :: 3.11
Classifier: Framework :: FastAPI
Classifier: Operating System :: OS Independent
Requires-Python: >=3.7
License-File: LICENSE.md
Requires-Dist: fastapi
Requires-Dist: pydantic
Requires-Dist: sqlalchemy
Dynamic: license-file
